[
  {
    "subject": "Afghanistan national football team",
    "predicate": "category",
    "object": "national football team"
  },
  {
    "subject": "Afghanistan national football team",
    "predicate": "caption",
    "object": "Afghanistan"
  },
  {
    "subject": "Afghanistan national football team",
    "predicate": "infobox-image",
    "object": "Shirt badge/Association crest"
  },
  {
    "subject": "Afghanistan national football team",
    "predicate": "Nickname(s)",
    "object": "The Lions of Khorasan"
  },
  {
    "subject": "Afghanistan national football team",
    "predicate": "Association",
    "object": "Afghanistan Football Federation"
  },
  {
    "subject": "Afghanistan national football team",
    "predicate": "Confederation",
    "object": "AFC (Asia)"
  },
  {
    "subject": "Afghanistan national football team",
    "predicate": "Sub-confederation",
    "object": "CAFA (Central Asia)"
  },
  {
    "subject": "Afghanistan national football team",
    "predicate": "Head coach",
    "object": "Anoush Dastgir"
  },
  {
    "subject": "Afghanistan national football team",
    "predicate": "Captain",
    "object": "Farshad Noor"
  },
  {
    "subject": "Afghanistan national football team",
    "predicate": "Most caps",
    "object": "Zohib Islam Amiri (65)"
  },
  {
    "subject": "Afghanistan national football team",
    "predicate": "Top scorer",
    "object": "Faysal Shayesteh (10)"
  },
  {
    "subject": "Afghanistan national football team",
    "predicate": "Home stadium",
    "object": "Ghazi Stadium"
  },
  {
    "subject": "Afghanistan national football team",
    "predicate": "FIFA code",
    "object": "AFG"
  },
  {
    "subject": "Afghanistan national football team",
    "predicate": "First colours",
    "object": "Second colours"
  },
  {
    "subject": "Afghanistan national football team",
    "predicate": "FIFA ranking-current",
    "object": "154 | Decrease |  4 (23 June 2022)"
  },
  {
    "subject": "Afghanistan national football team",
    "predicate": "FIFA ranking-highest",
    "object": "122 (April 2014)"
  },
  {
    "subject": "Afghanistan national football team",
    "predicate": "FIFA ranking-lowest",
    "object": "204 (January 2003)"
  },
  {
    "subject": "Afghanistan national football team",
    "predicate": "First international-unofficial",
    "object": "Afghanistan 0-0 Iran (Kabul, Afghanistan; 25 August 1941)"
  },
  {
    "subject": "Afghanistan national football team",
    "predicate": "First international-official",
    "object": "Luxembourg 6-0 Afghanistan (Brighton, England; 26 July 1948)"
  },
  {
    "subject": "Afghanistan national football team",
    "predicate": "Biggest win",
    "object": "Bhutan 1-8 Afghanistan (New Delhi, India; 7 December 2011)"
  },
  {
    "subject": "Afghanistan national football team",
    "predicate": "Biggest defeat",
    "object": "Turkmenistan 11-0 Afghanistan (Ashgabat, Turkmenistan; 19 November 2003)"
  },
  {
    "subject": "Afghanistan national football team",
    "predicate": "AFC Challenge Cup-Appearances",
    "object": "3 (first in 2006)"
  },
  {
    "subject": "Afghanistan national football team",
    "predicate": "AFC Challenge Cup-Best result",
    "object": "Fourth place (2014)"
  },
  {
    "subject": "Afghanistan national football team",
    "predicate": "SAFF Championship-Gold medal",
    "object": "2013 Nepal"
  },
  {
    "subject": "Afghanistan national football team",
    "predicate": "SAFF Championship-Silver medal",
    "object": "2011 India"
  },
  {
    "subject": "Afghanistan national football team",
    "predicate": "SAFF Championship-Silver medal",
    "object": "2015 India"
  },
  {
    "subject": "Afghanistan national football team",
    "predicate": "Men's football",
    "object": ""
  }
]