[
  {
    "subject": "Triple H",
    "predicate": "category",
    "object": "wrestling"
  },
  {
    "subject": "Triple H",
    "predicate": "Born",
    "object": "Paul Michael Levesque | ( | 1969-07-27 | ) | July 27, 1969 | (age 52) | Nashua, New Hampshire, U.S."
  },
  {
    "subject": "Triple H",
    "predicate": "Occupation",
    "object": "Business executive | professional wrestler | actor"
  },
  {
    "subject": "Triple H",
    "predicate": "Years active",
    "object": "1992-2022 (wrestling) | 2010-present (business) | 1998-2017 (acting)"
  },
  {
    "subject": "Triple H",
    "predicate": "Employer",
    "object": "WWE"
  },
  {
    "subject": "Triple H",
    "predicate": "Title",
    "object": "Executive Vice President of Global Talent Strategy & Development"
  },
  {
    "subject": "Triple H",
    "predicate": "Spouse(s)",
    "object": "Stephanie McMahon | ( | married | 2003 | )"
  },
  {
    "subject": "Triple H",
    "predicate": "Children",
    "object": "3"
  },
  {
    "subject": "Triple H",
    "predicate": "Family",
    "object": "McMahon"
  },
  {
    "subject": "Triple H",
    "predicate": "Triple H",
    "object": "Triple H November 2017.jpg | Triple H in November 2017"
  },
  {
    "subject": "Professional wrestling career",
    "predicate": "Ring name(s)",
    "object": "Hunter Hearst Helmsley | Jean-Paul Lévesque | Terra Risin' | Terra Ryzing | Terror Rising | Triple H"
  },
  {
    "subject": "Professional wrestling career",
    "predicate": "Billed height",
    "object": "6 ft 4 in (193 cm)"
  },
  {
    "subject": "Professional wrestling career",
    "predicate": "Billed weight",
    "object": "255 lb (116 kg)"
  },
  {
    "subject": "Professional wrestling career",
    "predicate": "Billed from",
    "object": "Boston, Massachusetts, U.S. | Greenwich, Connecticut, U.S. | Sainte-Mere-Eglise, France"
  },
  {
    "subject": "Professional wrestling career",
    "predicate": "Trained by",
    "object": "Killer Kowalski"
  },
  {
    "subject": "Professional wrestling career",
    "predicate": "Debut",
    "object": "1992"
  },
  {
    "subject": "Professional wrestling career",
    "predicate": "Retired",
    "object": "2022"
  }
]