[
  {
    "subject": "Whitney Houston",
    "predicate": "is a",
    "object": "musician"
  },
  {
    "subject": "Whitney Houston",
    "predicate": "Born",
    "object": "Whitney Elizabeth Houston | ( | 1963-08-09 | ) | August 9, 1963 | Newark, New Jersey, U.S."
  },
  {
    "subject": "Whitney Houston",
    "predicate": "Died",
    "object": "February 11, 2012 | (2012-02-11) |  (aged 48) | Beverly Hills, California, U.S."
  },
  {
    "subject": "Whitney Houston",
    "predicate": "Cause of death",
    "object": "Drowning due to coronary artery disease and cocaine intoxication"
  },
  {
    "subject": "Whitney Houston",
    "predicate": "Resting place",
    "object": "Fairview Cemetery, | Westfield, New Jersey, U.S."
  },
  {
    "subject": "Whitney Houston",
    "predicate": "Education",
    "object": "Mount Saint Dominic Academy"
  },
  {
    "subject": "Whitney Houston",
    "predicate": "Occupation",
    "object": "Singer | actress | producer | model"
  },
  {
    "subject": "Whitney Houston",
    "predicate": "Years active",
    "object": "1977-2012"
  },
  {
    "subject": "Whitney Houston",
    "predicate": "Spouse(s)",
    "object": "Bobby Brown | ( | married |  1992; | divorced |  2007)"
  },
  {
    "subject": "Whitney Houston",
    "predicate": "Children",
    "object": "Bobbi Kristina Brown"
  },
  {
    "subject": "Whitney Houston",
    "predicate": "Parent(s)",
    "object": "Cissy Houston (mother)"
  },
  {
    "subject": "Whitney Houston",
    "predicate": "Relatives",
    "object": "Gary Garland (half-brother) | Dionne Warwick (cousin) | Dee Dee Warwick (cousin) | Leontyne Price (cousin)"
  },
  {
    "subject": "Whitney Houston",
    "predicate": "Awards",
    "object": "Full list"
  },
  {
    "subject": "Whitney Houston",
    "predicate": "image",
    "object": "Whitney Houston (cropped3).JPEG | Houston performing on her | Welcome Home Heroes | concert in 1991"
  },
  {
    "subject": "Whitney Houston's Musical career",
    "predicate": "Genres",
    "object": "R&B | pop | soul | gospel | dance"
  },
  {
    "subject": "Whitney Houston's Musical career",
    "predicate": "Labels",
    "object": "Arista | RCA"
  },
  {
    "subject": "Whitney Houston's Musical career",
    "predicate": "Associated acts",
    "object": "Jermaine Jackson | Stevie Wonder | Bobby Brown | Mariah Carey | George Michael | CeCe Winans"
  },
  {
    "subject": "Whitney Houston's Musical career",
    "predicate": "Website",
    "object": "whitneyhouston.com"
  },
  {
    "subject": "Whitney Houston",
    "predicate": "Signature",
    "object": "WhitneyHoustonSignature.svg"
  }
]