[
  {
    "subject": "Sylvester Croom",
    "predicate": "category",
    "object": "nfl"
  },
  {
    "subject": "Sylvester Croom",
    "predicate": "infobox-image",
    "object": "Croom at Tennessee Titans training camp in 2014"
  },
  {
    "subject": "Sylvester Croom",
    "predicate": "No. 51",
    "object": "Center"
  },
  {
    "subject": "Sylvester Croom",
    "predicate": "Born",
    "object": "September 25, 1954 (age 67) in Tuscaloosa, Alabama"
  },
  {
    "subject": "Sylvester Croom",
    "predicate": "Height",
    "object": "6 ft 0 in (1.83 m)"
  },
  {
    "subject": "Sylvester Croom",
    "predicate": "Weight",
    "object": "235 lb (107 kg)"
  },
  {
    "subject": "Sylvester Croom",
    "predicate": "High school",
    "object": "Tuscaloosa (AL)"
  },
  {
    "subject": "Sylvester Croom",
    "predicate": "College",
    "object": "Alabama (1972-1974)"
  },
  {
    "subject": "Sylvester Croom",
    "predicate": "Undrafted",
    "object": "1975"
  },
  {
    "subject": "Sylvester Croom",
    "predicate": "As a player",
    "object": "New Orleans Saints (1975)"
  },
  {
    "subject": "Sylvester Croom",
    "predicate": "As a coach",
    "object": "Alabama, Tampa Bay Buccaneers, Indianapolis Colts, San Diego Chargers, Detroit Lions, Green Bay Packers, Mississippi State, St. Louis Rams, Jacksonville Jaguars, Tennessee Titans"
  },
  {
    "subject": "Sylvester Croom",
    "predicate": "Career highlights and awards",
    "object": "SEC Coach of the Year (2007), Liberty Mutual Fan Coach of the Year (2007), College All-American (1974)"
  },
  {
    "subject": "Sylvester Croom",
    "predicate": "Head coaching record",
    "object": "21-38 (college)"
  },
  {
    "subject": "Sylvester Croom",
    "predicate": "Player stats",
    "object": "NFL.com"
  },
  {
    "subject": "Sylvester Croom",
    "predicate": "Coaching stats",
    "object": "PFR"
  }
]