[
  {
    "subject": "Bill Hosket",
    "predicate": "category",
    "object": "basketball"
  },
  {
    "subject": "Bill Hosket",
    "predicate": "infobox-image",
    "object": "Bill Hosket Jr 1969.jpg | Hosket in 1969"
  },
  {
    "subject": "Bill Hosket",
    "predicate": "Born",
    "object": "( | 1946-12-20 | ) | December 20, 1946 | (age 75) | Dayton, Ohio"
  },
  {
    "subject": "Bill Hosket",
    "predicate": "Nationality",
    "object": "American"
  },
  {
    "subject": "Bill Hosket",
    "predicate": "Listed height",
    "object": "6 ft 8 in (2.03 m)"
  },
  {
    "subject": "Bill Hosket",
    "predicate": "Listed weight",
    "object": "225 lb (102 kg)"
  },
  {
    "subject": "Bill Hosket",
    "predicate": "High school",
    "object": "Belmont (Dayton, Ohio)"
  },
  {
    "subject": "Bill Hosket",
    "predicate": "College",
    "object": "Ohio State (1965-1968)"
  },
  {
    "subject": "Bill Hosket",
    "predicate": "NBA draft",
    "object": "1968 / Round: 1 / Pick: 10th overall"
  },
  {
    "subject": "Bill Hosket",
    "predicate": "Playing career",
    "object": "1968-1972"
  },
  {
    "subject": "Bill Hosket",
    "predicate": "Position",
    "object": "Power forward / Center"
  },
  {
    "subject": "Bill Hosket",
    "predicate": "Number",
    "object": "20, 25"
  },
  {
    "subject": "Bill Hosket",
    "predicate": "Selected by",
    "object": "New York Knicks"
  },
  {
    "subject": "Bill Hosket",
    "predicate": "1968-1970",
    "object": "New York Knicks"
  },
  {
    "subject": "Bill Hosket",
    "predicate": "1970-1972",
    "object": "Buffalo Braves"
  },
  {
    "subject": "Bill Hosket",
    "predicate": "NBA champion",
    "object": "1970"
  },
  {
    "subject": "Bill Hosket",
    "predicate": "Fourth-team",
    "object": "Parade All-American (1964)"
  },
  {
    "subject": "Bill Hosket",
    "predicate": "Points",
    "object": "573 (4.0 ppg)"
  },
  {
    "subject": "Bill Hosket",
    "predicate": "Rebounds",
    "object": "355 (2.5 rpg)"
  },
  {
    "subject": "Bill Hosket",
    "predicate": "Assists",
    "object": "94 (0.7 apg)"
  },
  {
    "subject": "Bill Hosket",
    "predicate": "Representing",
    "object": "United States"
  },
  {
    "subject": "Bill Hosket",
    "predicate": "Gold medal - first place",
    "object": "1968 Mexico City Team competition"
  }
]