[
  {"subject": "University of Cambridge", "predicate": "category", "object": "university"},
  {"subject": "University of Cambridge", "predicate": "infobox-image", "object": "University of Cambridge coat of arms.svg | Coat of arms"},
  {"subject": "University of Cambridge", "predicate": "Other name", "object": "The Chancellor, Masters and Scholars of the University of Cambridge"},
  {"subject": "University of Cambridge", "predicate": "Motto", "object": "Latin | Hinc lucem et pocula sacra"},
  {"subject": "University of Cambridge", "predicate": "Motto in English", "object": "Literal: From here, light and sacred draughts. Non literal: From this place, we gain enlightenment and precious knowledge."},
  {"subject": "University of Cambridge", "predicate": "Type", "object": "Public research university"},
  {"subject": "University of Cambridge", "predicate": "Established", "object": "circa | 1209 | ; 813 years ago | ( | 1209 | )"},
  {"subject": "University of Cambridge", "predicate": "Academic affiliations", "object": "Russell Group | EUA | G5 Universities | Golden Triangle | LERU | IARU | Universities UK"},
  {"subject": "University of Cambridge", "predicate": "Endowment", "object": "£7.121 billion (including colleges)"},
  {"subject": "University of Cambridge", "predicate": "Budget", "object": "£2.308 billion (excluding colleges)"},
  {"subject": "University of Cambridge", "predicate": "Chancellor", "object": "The Lord Sainsbury of Turville"},
  {"subject": "University of Cambridge", "predicate": "Vice-Chancellor", "object": "Stephen J. Toope"},
  {"subject": "University of Cambridge", "predicate": "Academic staff", "object": "6,170 (2020)"},
  {"subject": "University of Cambridge", "predicate": "Administrative staff", "object": "3,615 (excluding colleges)"},
  {"subject": "University of Cambridge", "predicate": "Students", "object": "24,450 (2020)"},
  {"subject": "University of Cambridge", "predicate": "Undergraduates", "object": "12,850 (2020)"},
  {"subject": "University of Cambridge", "predicate": "Postgraduates", "object": "11,600 (2020)"},
  {"subject": "University of Cambridge", "predicate": "Location", "object": "Cambridge | , | England"},
  {"subject": "University of Cambridge", "predicate": "Campus", "object": "University town | 288 hectares (710 acres)"},
  {"subject": "University of Cambridge", "predicate": "Colours", "object": "Cambridge Blue"},
  {"subject": "University of Cambridge", "predicate": "Sporting affiliations", "object": "The Sporting Blue"},
  {"subject": "University of Cambridge", "predicate": "Website", "object": "cam | .ac | .uk"}
]