[
  {
    "subject": "Max Aaron",
    "predicate": "category",
    "object": "figure skating"
  },
  {
    "subject": "Max Aaron",
    "predicate": "image",
    "object": "Max Aaron - 2016 Worlds.jpg"
  },
  {
    "subject": "Max Aaron",
    "predicate": "description",
    "object": "Aaron during the exhibition gala at the 2016 World Championships"
  },
  {
    "subject": "Max Aaron",
    "predicate": "full name",
    "object": "Maxwell Theodore Aaron"
  },
  {
    "subject": "Max Aaron",
    "predicate": "country represented",
    "object": "United States"
  },
  {
    "subject": "Max Aaron",
    "predicate": "born",
    "object": "February 25, 1992"
  },
  {
    "subject": "Max Aaron",
    "predicate": "age",
    "object": "30"
  },
  {
    "subject": "Max Aaron",
    "predicate": "birth place",
    "object": "Scottsdale, Arizona"
  },
  {
    "subject": "Max Aaron",
    "predicate": "home town",
    "object": "Scottsdale, Arizona"
  },
  {
    "subject": "Max Aaron",
    "predicate": "residence",
    "object": "Colorado Springs, Colorado"
  },
  {
    "subject": "Max Aaron",
    "predicate": "height",
    "object": "1.73 m (5 ft 8 in)"
  },
  {
    "subject": "Max Aaron",
    "predicate": "coach",
    "object": "Tom Zakrajsek, Becky Calvin"
  },
  {
    "subject": "Max Aaron",
    "predicate": "former coach",
    "object": "Julie Patterson, Doug Ladret"
  },
  {
    "subject": "Max Aaron",
    "predicate": "choreographer",
    "object": "Katherine Hill"
  },
  {
    "subject": "Max Aaron",
    "predicate": "former choreographer",
    "object": "Phillip Mills, Mark Pillay, Lori Nichol, Pasquale Camerlengo, Tom Dickson, Catarina Lindgren"
  },
  {
    "subject": "Max Aaron",
    "predicate": "skating club",
    "object": "Broadmoor SC"
  },
  {
    "subject": "Max Aaron",
    "predicate": "began skating",
    "object": "1996"
  },
  {
    "subject": "Max Aaron",
    "predicate": "retired",
    "object": "April 19, 2018"
  },
  {
    "subject": "Max Aaron",
    "predicate": "world standing",
    "object": "12 (2017-18), 13 (2016-17), 11 (2015-16), 11 (2014-15), 14 (2013-14), 27 (2012-13), 56 (2011-12), 59 (2010-11)"
  },
  {
    "subject": "Max Aaron",
    "predicate": "ISU personal best scores(combined total)",
    "object": "261.56 (2017 U.S. Classic)"
  },
  {
    "subject": "Max Aaron",
    "predicate": "ISU personal best scores(short program)",
    "object": "87.03 (2015 Tallinn Trophy)"
  },
  {
    "subject": "Max Aaron",
    "predicate": "ISU personal best scores(free skate)",
    "object": "176.58 (2017 Cup of China)"
  },
  {
    "subject": "Max Aaron",
    "predicate": "figure skating event",
    "object": "men's singles"
  },
  {
    "subject": "Max Aaron",
    "predicate": "representing",
    "object": "United States"
  },
  {
    "subject": "Max Aaron",
    "predicate": "World Team Trophy",
    "object": "Gold medal - first place (2013 Tokyo, Team), Gold medal - first place (2015 Tokyo, Team)"
  }
]