[
    {"subject": "Mondher Zenaidi", "predicate": "category", "object": "office holder"},
    {"subject": "Mondher Zenaidi", "predicate": "Arabic name", "object": "منذر الزنايدي"},
    {"subject": "Mondher Zenaidi", "predicate": "image", "object": "Mondher Zenaidi.JPG"},
    {"subject": "Mondher Zenaidi", "predicate": "Minister of Public Health", "object": "In office | 3 September 2007 - 17 January 2011"},
    {"subject": "In office | 3 September 2007 - 17 January 2011", "predicate": "President", "object": "Zine el-Abidine Ben Ali"},
    {"subject": "In office | 3 September 2007 - 17 January 2011", "predicate": "Prime Minister", "object": "Mohamed Ghannouchi"},
    {"subject": "In office | 3 September 2007 - 17 January 2011", "predicate": "Preceded by", "object": "Mohamed Ridha Kechrid"},
    {"subject": "In office | 3 September 2007 - 17 January 2011", "predicate": "Succeeded by", "object": "Mustapha Ben Jaafar"},
    {"subject": "Mondher Zenaidi", "predicate": "Minister of Commerce", "object": "In office | 5 September 2002 - 3 September 2007"},
    {"subject": "In office | 5 September 2002 - 3 September 2007", "predicate": "President", "object": "Zine el-Abidine Ben Ali"},
    {"subject": "In office | 5 September 2002 - 3 September 2007", "predicate": "Prime Minister", "object": "Mohamed Ghannouchi"},
    {"subject": "In office | 5 September 2002 - 3 September 2007", "predicate": "Preceded by", "object": "Tahar Sioud"},
    {"subject": "In office | 5 September 2002 - 3 September 2007", "predicate": "Succeeded by", "object": "Ridha Touiti"},
    {"subject": "Mondher Zenaidi", "predicate": "Minister of Tourism", "object": "In office | 25 January 2001 - 22 March 2004"},
    {"subject": "In office | 25 January 2001 - 22 March 2004", "predicate": "President", "object": "Zine el-Abidine Ben Ali"},
    {"subject": "In office | 25 January 2001 - 22 March 2004", "predicate": "Prime Minister", "object": "Mohamed Ghannouchi"},
    {"subject": "Mondher Zenaidi", "predicate": "Minister of Tourism", "object": "In office | 13 June 1996 - 25 January 2001"},
    {"subject": "In office | 13 June 1996 - 25 January 2001", "predicate": "President", "object": "Zine el-Abidine Ben Ali"},
    {"subject": "In office | 13 June 1996 - 25 January 2001", "predicate": "Prime Minister", "object": "Hamed Karoui | Mohamed Ghannouchi"},
    {"subject": "In office | 13 June 1996 - 25 January 2001", "predicate": "Preceded by", "object": "Slaheddine Ben Mbarek"},
    {"subject": "In office | 13 June 1996 - 25 January 2001", "predicate": "Succeeded by", "object": "Tahar Sioud"},
    {"subject": "Mondher Zenaidi", "predicate": "Minister of Transport", "object": "In office | 1 June 1994 - 13 June 1996"},
    {"subject": "In office | 1 June 1994 - 13 June 1996", "predicate": "President", "object": "Zine el-Abidine Ben Ali"},
    {"subject": "In office | 1 June 1994 - 13 June 1996", "predicate": "Prime Minister", "object": "Hamed Karoui"},
    {"subject": "In office | 1 June 1994 - 13 June 1996", "predicate": "Preceded by", "object": "Tahar Hadj Ali"},
    {"subject": "In office | 1 June 1994 - 13 June 1996", "predicate": "Succeeded by", "object": "Sadok Rabah"},
    {"subject": "Mondher Zenaidi", "predicate": "birthdate", "object": "24 October 1950"},
    {"subject": "Mondher Zenaidi", "predicate": "birthplace", "object": "Tunis, Tunisia"},
    {"subject": "Mondher Zenaidi", "predicate": "age", "object": "71"},
    {"subject": "Mondher Zenaidi", "predicate": "political party", "object": "independent"},
    {"subject": "Mondher Zenaidi", "predicate": "other political affiliations", "object": "Democratic Constitutional Rally | (-2011)"},
    {"subject": "Mondher Zenaidi", "predicate": "children", "object": "2"},
    {"subject": "Mondher Zenaidi", "predicate": "alma mater", "object": "École Centrale Paris, ENA"}
]