{"category": "squash", "caption": "Ali Farag", "infobox-image": "Ali Farag 2017.jpg | Farag at the 2017 Men's World Team Squash Championships", "Full name": "Ali Amr Farag", "Nickname(s)": "Mr. Fantastic, Rubber-band Man, The Raptor", "Country": "Egypt", "Residence": "Cairo, Egypt", "Born": "( | 1992-04-22 | ) | 22 April 1992 | (age 30) | Cairo, Egypt", "Height": "1.83 m (6 ft 0 in)", "Turned Pro": "2009", "Retired": "Active", "Plays": "Right handed", "Coached by": "Wael Farag, Mike Way, Basem Makram, Karim Darwish", "Racquet used": "Dunlop HyperfibreXT Revelation Pro", "Website": "Ali Farag on Twitter | dunlopsports | .com | /team | /squash | /pros | /ali-farag | /", "Men's singles": {"Highest ranking": "No. 1 (June 2022)", "Current ranking": "No. 1 (June 2022)", "Title(s)": "22", "Tour final(s)": "41", "World Open": "W | (2020-21)"}, "Men's squash": {}, "Representing | Egypt": {}, "World Championships": {"World Championships": ["Bronze medal - third place | 2017 Manchester | Singles", "Gold medal - first place | 2018-19 Chicago | Singles", "Gold medal - first place | 2020-21 Chicago | Singles", "Gold medal - first place | 2021-22 Cairo | Singles"]}, "World Team Championships": {"World Team Championships": ["Gold medal - first place | 2017 Marseille | Team", "Gold medal - first place | 2019 Washington D.C. | Team"]}, "Last updated: May 2022.": {}}