{"category": "character", "Judah Ben-Hur": {"First appearance": "A Tale of the Christ | (1880, novel)", "Last appearance": "Ben-Hur | (2016, film)", "Created by": "Lew Wallace", "Portrayed by": "Ramon Novarro (1925) | Charlton Heston (1959) | Joseph Morgan (2010) | Jack Huston (2016)", "Voiced by": "Charlton Heston (2003)", "Judah Ben-Hur": ["Ben-Hur | character", "Charlton Heston in Ben Hur trailer.jpg | Charlton Heston as Judah Ben-Hur from | Ben-Hur | (1959)"]}, "In-universe information": {"Alias": "Ben-Hur | Son of Hur | Young Arrius", "Gender": "Male", "Occupation": "Prince | Galley Slave | Charioteer", "Family": "Miriam (mother) | Tirzah (sister)", "Spouse": "Esther"}}