{"category": "empire", "Crimean Khanate | Q\u0131r\u0131m Hanl\u0131\u011f\u0131 | (Crimean Tatar) | \u0642\u0631\u0645 \u062e\u0627\u0646\u0644\u063a\u0649 | (Crimean Tatar)": {"Status": "Khanate", "Capital": "Orda-i muazzam Kirkyir | Eski Q\u0131r\u0131m | Ba\u011f\u00e7asaray", "Common languages": "Kipchak dialects (Crimean Tatar, Nogai and others) | Ottoman Turkish | language of literature - Chagatai language", "Religion": "Sunni Islam", "Demonym(s)": "Crimean", "Government": "Elective monarchy", "Khan": "", " 1441-1466": "Hac\u0131 I Giray | (First)", " 1777-1783": "\u015eahin Giray | (last)", "History": "", " Established": "1441", " Annexed by Russia": "1783", "Preceded by": "Succeeded by", "Today part of": "Moldova | Russia | Ukraine", "Crimean Khanate | Q\u0131r\u0131m Hanl\u0131\u011f\u0131 | (Crimean Tatar) | \u0642\u0631\u0645 \u062e\u0627\u0646\u0644\u063a\u0649 | (Crimean Tatar)": ["1441-1783", "Coat of arms of the Crimean Khanate | Insignia of the Giray dynasty | Coat of arms | Insignia of the Giray dynasty", "The khanate in 1550 | The khanate in 1550", "Golden Horde", "Principality of Theodoro", "Russian Empire"]}}