{"category": "country", "Democratic People's | Republic of Korea | \uc870\uc120\ubbfc\uc8fc\uc8fc\uc758\uc778\ubbfc\uacf5\ud654\uad6d | (Korean) | Chos\u014fn Minjuju\u016di Inmin Konghwaguk |  (MR)": {"Democratic People's | Republic of Korea | \uc870\uc120\ubbfc\uc8fc\uc8fc\uc758\uc778\ubbfc\uacf5\ud654\uad6d | (Korean) | Chos\u014fn Minjuju\u016di Inmin Konghwaguk |  (MR)": ["Flag of North Korea | Flag | Emblem of North Korea | Emblem"]}, "Motto | \uac15\uc131\ub300\uad6d | Kangs\u014fngdaeguk | \"Strong and Prosperous Nation\"": {}, "Anthem | \uc560\uad6d\uac00 | Aegukka | \"The Patriotic Song\"": {}, "Dark green: Territory controlled by the DPRK Lighter green: Territory claimed but uncontrolled by the DPRK | Dark green |  Territory controlled by the DPRK | Lighter green |  Territory claimed but uncontrolled by the DPRK": {"Capital | and largest city": "Pyongyang | 39\u00b02\u2032N | 125\u00b045\u2032E |  / | 39.033\u00b0N 125.750\u00b0E |  / | 39.033; 125.750", "Official languages": "Korean (Munhwa\u014f)", "Official script": "Chos\u014fn'g\u016dl", "Religion": "State atheism", "Demonym(s)": "North Korean | Korean", "Government": "Unitary Jucheist one-party socialist parliamentary republic under a totalitarian hereditary dictatorship", " General Secretary of the WPK and President of the SAC": "Kim Jong-un", " Chairman of the SPA Standing Committee and First Vice President of the SAC": "Choe Ryong-hae", " Vice President of the SAC and Premier of Cabinet": "Kim Tok-hun", " Chairman of the SPA": "Pak Thae-song", "Legislature": "Supreme People's Assembly"}, "Formation": {" Soviet administration": "3 October 1945", " 1st provisional govt.": "8 February 1946", " 2nd provisional govt.": "22 February 1947", " DPRK established": "9 September 1948", " Current constitution": "27 December 1972", " Admitted to the UN": "17 September 1991", "Panmunjom Declaration": "27 April 2018"}, "Area": {" Total": "120,540 km | 2 |  (46,540 sq mi) (97th)", " Water (%)": "0.11"}, "Population": {" 2018 estimate": "25,549,604 (55th)", " 2008 census": "24,052,231", " Density": "212/km | 2 |  (549.1/sq mi) (45th)", "GDP | .mw-parser-output .nobold{font-weight:normal} | (PPP)": "2015 estimate", " Total": "$30 billion", " Per capita": "$1,300", "GDP | (nominal)": "2017 estimate", "Currency": "Korean People's won (\u20a9) (KPW)", "Time zone": "UTC+9 |  (Pyongyang Time)", "Date format": "yy, | yyyy\ub144 mm\uc6d4 dd\uc77c | yy, yyyy/mm/dd | (AD-1911 / AD)", "Driving side": "right", "Calling code": "+850", "ISO 3166 code": "KP", "Internet TLD": ".kp"}}