{"category": "golf", "Harry Cooper": {"Harry Cooper": ["Golfer Harry Cooper 1936.jpg | Cooper at the 1936 Masters Tournament"]}, "Personal information": {"Full name": "Henry Edward Cooper", "Nickname": "Lighthorse Harry", "Born": "( | 1904-08-04 | ) | August 4, 1904 | Leatherhead, England", "Died": "October 17, 2000 | (2000-10-17) | (aged 96) | White Plains, New York, US", "Height": "5 ft 8.5 in (1.74 m)", "Weight": "152 lb (69 kg; 10.9 st)", "Sporting nationality": "England | United States", "Spouse": "Emma Buchanan Cooper (1910-2002)"}, "Career": {"Turned professional": "1923", "Former tour(s)": "PGA Tour", "Professional wins": "36"}, "Number of wins by tour": {"PGA Tour": "30", "Other": "6"}, "Best results in major championships": {"Masters Tournament": "2nd/T2: 1936, 1938", "PGA Championship": "T3: 1925", "U.S. Open": "2nd: 1927, 1936", "The Open Championship": "DNP"}, "Achievements and awards": {"World Golf Hall of Fame": "1992 | (member page)", "Vardon Trophy": "1937", "PGA Tour | leading money winner": "1937"}}