{"category": "swimming", "caption": "Alexander Popov", "infobox-image": "Alexander Popov 006.jpg", "Personal information": {"Full name": "\u0410\u043b\u0435\u043a\u0441\u0430\u0301\u043d\u0434\u0440 \u0412\u043b\u0430\u0434\u0438\u0301\u043c\u0438\u0440\u043e\u0432\u0438\u0447 \u041f\u043e\u043f\u043e\u0301\u0432 | Alexander Vladimirovich Popov", "Nickname(s)": "The Russian Rocket, Czar of Swimming, King of Short Distance", "Nationality": "Russian", "Born": "( | 1971-11-16 | ) | 16 November 1971 | (age 50) | Lesnoy, Sverdlovsk, Russian SFSR, Soviet Union", "Height": "2.01 m (6 ft 7 in)", "Weight": "87 kg (192 lb)"}, "Sport": {"Sport": ["Event | 1 | st | 2 | nd | 3 | rd", "Olympic Games | 4 | 5 | 0", "World Championships (LC) | 6 | 4 | 1", "World Championships (SC) | 0 | 0 | 2", "European Championships (LC) | 21 | 3 | 2", "European Championships (SC) | 2 | 0 | 0", "Total | 33 | 12 | 5"], "Strokes": "Freestyle | 1989\uff0d2005 | Backstroke | 1979-1989", "Club": "Dynamo Moscow"}, "Olympic Games": {}, "Representing | the |  Unified Team": {"Representing | the |  Unified Team": ["Gold medal - first place | 1992 Barcelona | 50 m freestyle", "Gold medal - first place | 1992 Barcelona | 100 m freestyle", "Silver medal - second place | 1992 Barcelona | 4\u00d7100 m freestyle", "Silver medal - second place | 1992 Barcelona | 4\u00d7100 m medley"]}, "Representing | Russia": {"Representing | Russia": ["Gold medal - first place | 1993 Sheffield | 50 m freestyle", "Gold medal - first place | 1993 Sheffield | 100 m freestyle", "Gold medal - first place | 1993 Sheffield | 4\u00d7100 m freestyle", "Gold medal - first place | 1993 Sheffield | 4\u00d7100 m medley", "Gold medal - first place | 1995 Vienna | 50 m freestyle", "Gold medal - first place | 1995 Vienna | 100 m freestyle", "Gold medal - first place | 1995 Vienna | 4\u00d7100 m freestyle", "Gold medal - first place | 1995 Vienna | 4\u00d7100 m medley", "Gold medal - first place | 1997 Seville | 50 m freestyle", "Gold medal - first place | 1997 Seville | 100 m freestyle", "Gold medal - first place | 1997 Seville | 4\u00d7100 m freestyle", "Gold medal - first place | 1997 Seville | 4\u00d7100 m medley", "Gold medal - first place | 2000 Helsinki | 50 m freestyle", "Gold medal - first place | 2000 Helsinki | 100 m freestyle", "Gold medal - first place | 2000 Helsinki | 4\u00d7100 m freestyle", "Gold medal - first place | 2000 Helsinki | 4\u00d7100 m medley", "Gold medal - first place | 2002 Berlin | 4\u00d7100 m medley", "Gold medal - first place | 2004 Madrid | 50 m freestyle", "Silver medal - second place | 1999 Istanbul | 100 m freestyle", "Silver medal - second place | 1999 Istanbul | 4\u00d7100 m freestyle", "Silver medal - second place | 2002 Berlin | 100 m freestyle", "Bronze medal - third place | 1999 Istanbul | 50 m freestyle", "Bronze medal - third place | 1999 Istanbul | 4\u00d7100 m medley"]}, "World Championships (LC)": {}, "World Championships (SC)": {}, "European Championships (LC)": {}, "Representing | Soviet Union": {"Representing | Soviet Union": ["Gold medal - first place | 1991 Gelsenkirchen | 50 m freestyle", "Gold medal - first place | 1991 Gelsenkirchen | 4\u00d750 m medley relay", "Silver medal - second place | 1991 Gelsenkirchen | 4\u00d750 m freestyle relay"]}, "European Championships (SC)": {}}