{"category": "hockey", "caption": "Jorge Lombi", "Personal information": {"Born": "November 1, 1971"}, "Men\u2019s Field Hockey": {}, "Representing | Argentina": {}, "Champions Challenge": {"Champions Challenge": ["Bronze medal - third place | 2001 Kuala Lumpur | Team", "Gold medal - first place | 2005 Alexandria | Team", "Gold medal - first place | 2007 Boom | Team"]}, "Pan American Games": {"Pan American Games": ["Gold medal - first place | 1995 Mar del Plata | Team", "Silver medal - second place | 1999 Winnipeg | Team", "Gold medal - first place | 2003 Santo Domingo | Team", "Gold medal - first place | 2007 Rio de Janeiro | Team"]}}